nonebot_plugin_uuid/__init__.py
nonebot_plugin_uuid/config.py
nonebot_plugin_uuid-0.1.4.dist-info/LICENSE
nonebot_plugin_uuid-0.1.4.dist-info/METADATA
nonebot_plugin_uuid-0.1.4.dist-info/WHEEL
nonebot_plugin_uuid-0.1.4.dist-info/RECORD
