Metadata-Version: 2.1
Name: nonebot-plugin-uuid
Version: 0.1.4
Summary: 一个生成 uuid 的 Nonebot2 插件
License: MIT
Author: ZombieFly
Author-email: xyzomfly@gmail.com
Requires-Python: >=3.8,<4.0
Classifier: License :: OSI Approved :: MIT License
Classifier: Programming Language :: Python :: 3
Classifier: Programming Language :: Python :: 3.8
Classifier: Programming Language :: Python :: 3.9
Classifier: Programming Language :: Python :: 3.10
Classifier: Programming Language :: Python :: 3.11
Requires-Dist: nonebot-adapter-onebot (>=2.2.1,<3.0.0)
Requires-Dist: nonebot2 (>=2.0.0b1,<3.0.0)
